ab_service/token_issuer/__init__.py
ab_service/token_issuer/main.py
ab_service/token_issuer/utils.py
ab_service/token_issuer/routes/__init__.py
ab_service/token_issuer/routes/run.py
ab_service/token_issuer/schema/__init__.py
ab_service/token_issuer/schema/run.py
ab_token_issuer_service-0.3.2.dist-info/METADATA
ab_token_issuer_service-0.3.2.dist-info/WHEEL
ab_token_issuer_service-0.3.2.dist-info/licenses/LICENSE
ab_token_issuer_service-0.3.2.dist-info/RECORD
