Metadata-Version: 2.4
Name: ab-token-issuer-service
Version: 0.3.2
Summary: A template package template.
Author-email: Matthew Coulter <53892067+mattcoulter7@users.noreply.github.com>
License-File: LICENSE
Requires-Python: <4,>=3.12
Requires-Dist: ab-cache<0.2.0,>=0.1.4
Requires-Dist: ab-logging<0.2.0,>=0.1.2
Requires-Dist: ab-token-issuer<0.3.0,>=0.2.3
Requires-Dist: fastapi<0.116,>=0.115.14
Requires-Dist: pydantic[email]<3,>=2.11.7
Requires-Dist: uvicorn<0.36,>=0.35.0
